ISENpy/Login.py
ISENpy/__init__.py
ISENpy/classification.py
ISENpy/client.py
ISENpy/dataClasses.py
ISENpy-0.7.0.dist-info/LICENSE
ISENpy-0.7.0.dist-info/METADATA
ISENpy-0.7.0.dist-info/WHEEL
ISENpy-0.7.0.dist-info/top_level.txt
ISENpy-0.7.0.dist-info/RECORD
