Metadata-Version: 2.1
Name: ISENpy
Version: 0.7.0
Summary: A python API wrapper for ISEN-OUEST
Home-page: https://github.com/CorentinMre/ISENpy
Author: CorentinMre
Author-email: corentin.marie@isen-ouest.yncrea.fr
License: MIT
Classifier: Programming Language :: Python :: 3
Classifier: License :: OSI Approved :: MIT License
Classifier: Operating System :: OS Independent
License-File: LICENSE
Requires-Dist: requests
Requires-Dist: bs4
Requires-Dist: lxml
